cloudnet_submit/__init__.py
cloudnet_submit/__main__.py
cloudnet_submit/cfg.py
cloudnet_submit/cloudnet-config-example.toml
cloudnet_submit/generate_config.py
cloudnet_submit/main.py
cloudnet_submit/py.typed
cloudnet_submit/submission.py
cloudnet_submit/utils.py
cloudnet_submit/version.py
cloudnet_submit-0.1.2.dist-info/licenses/LICENSE
cloudnet_submit-0.1.2.dist-info/METADATA
cloudnet_submit-0.1.2.dist-info/WHEEL
cloudnet_submit-0.1.2.dist-info/entry_points.txt
cloudnet_submit-0.1.2.dist-info/top_level.txt
cloudnet_submit-0.1.2.dist-info/RECORD
