Metadata-Version: 2.4
Name: cloudnet-submit
Version: 0.1.2
Summary: Cloudnet data submission tool
Author-email: Niko Leskinen <niko.leskinen@fmi.fi>
License: MIT License
Project-URL: Homepage, https://github.com/actris-cloudnet/cloudnet-submit
Project-URL: Repository, https://github.com/actris-cloudnet/cloudnet-submit
Project-URL: Changelog, https://github.com/actris-cloudnet/cloudnet-submit/blob/main/CHANGELOG.md
Project-URL: Bug Tracker, https://github.com/actris-cloudnet/cloudnet-submit/issues
Classifier: Development Status :: 4 - Beta
Classifier: Intended Audience :: Science/Research
Classifier: License :: OSI Approved :: MIT License
Classifier: Operating System :: OS Independent
Classifier: Programming Language :: Python :: 3
Classifier: Programming Language :: Python :: 3.10
Classifier: Programming Language :: Python :: 3.11
Classifier: Programming Language :: Python :: 3.12
Classifier: Programming Language :: Python :: 3.13
Classifier: Programming Language :: Python :: 3.8
Classifier: Programming Language :: Python :: 3.9
Requires-Python: >=3.8
License-File: LICENSE
Requires-Dist: braceexpand
Requires-Dist: requests>=2.28.1
Requires-Dist: toml>=0.10.2
Provides-Extra: dev
Requires-Dist: mypy; extra == "dev"
Requires-Dist: pre-commit; extra == "dev"
Requires-Dist: pytest; extra == "dev"
Requires-Dist: pytest-cov; extra == "dev"
Requires-Dist: types-requests; extra == "dev"
Requires-Dist: types-setuptools; extra == "dev"
Requires-Dist: types-toml; extra == "dev"
Provides-Extra: release
Requires-Dist: release-version; extra == "release"
Dynamic: license-file
